[
    {
        "title": "Análisis",
        "description": "Análisis de requerimientos del negocio, diseño de la solución y estructuración de sitios Web desde 0.",
        "icons": 0
    },
    {
        "title": "Desarrollo de Sitios Web",
        "description": "12 años de experiencia desarrollando páginas web auto administrables para cliente de Europa, Latam y USA.",
        "icons": 1
    },
    
    {
        "title": "Desarrollo de E-commerce",
        "description": "4 años desarrollando tiendas online e integrando con pasarelas de pago, facturación electronica y entrega.",
        "icons": 2

    },
    {
        "title": "Desarrollo de Aplicaciones Web",
        "description": "Desarrollo de aplicaciones web a medida mayormente tecnologías Javascript y PHP.",
        "icons": 3

    }

    ]